.gitignore
MANIFEST.in
README.txt
bootstrap.py
buildout.cfg
setup.cfg
setup.py
cs/__init__.py
cs.folderishpage.egg-info/PKG-INFO
cs.folderishpage.egg-info/SOURCES.txt
cs.folderishpage.egg-info/dependency_links.txt
cs.folderishpage.egg-info/entry_points.txt
cs.folderishpage.egg-info/namespace_packages.txt
cs.folderishpage.egg-info/not-zip-safe
cs.folderishpage.egg-info/requires.txt
cs.folderishpage.egg-info/top_level.txt
cs/folderishpage/INTEGRATION.txt
cs/folderishpage/__init__.py
cs/folderishpage/configure.zcml
cs/folderishpage/folderishpage.py
cs/folderishpage/permissions.zcml
cs/folderishpage/tests.py
cs/folderishpage/locales/README.txt
cs/folderishpage/profiles/default/metadata.xml
cs/folderishpage/profiles/default/rolemap.xml
cs/folderishpage/profiles/default/tinymce.xml
cs/folderishpage/profiles/default/types.xml
cs/folderishpage/profiles/default/types/FolderishPage.xml
cs/folderishpage/templates/folderishpageview.pt
cs/folderishpage/templates/folderishpagewithcontents.pt
docs/HISTORY.txt
docs/INSTALL.txt
docs/LICENSE.GPL
docs/LICENSE.txt