Metadata-Version: 1.1
Name: cs.folderishpage
Version: 1.1
Summary: Dexterity-based folderish page
Home-page: https://github.com/codesyntax/cs.folderishpage
Author: Mikel Larreategi
Author-email: mlarreategi@codesyntax.com
License: GPL
Keywords: plone page folder
Platform: UNKNOWN
Classifier: Framework :: Plone
Classifier: Programming Language :: Python
Classifier: Topic :: Software Development :: Libraries :: Python Modules
